dsis_client/__init__.py
dsis_client/api/__init__.py
dsis_client/api/auth/__init__.py
dsis_client/api/auth/auth.py
dsis_client/api/client/__init__.py
dsis_client/api/client/_base.py
dsis_client/api/client/_bulk_data.py
dsis_client/api/client/_http.py
dsis_client/api/client/_pagination.py
dsis_client/api/client/_query.py
dsis_client/api/client/base_client.py
dsis_client/api/client/dsis_client.py
dsis_client/api/config/__init__.py
dsis_client/api/config/config.py
dsis_client/api/config/environment.py
dsis_client/api/exceptions.py
dsis_client/api/models/__init__.py
dsis_client/api/models/schema_helper.py
dsis_client/api/models/serialization.py
dsis_client/api/query/__init__.py
dsis_client/api/query/builder.py
dsis_client/api/query/odata.py
dsis_client/py.typed
dsis_client-1.1.0.dist-info/licenses/LICENSE
dsis_client-1.1.0.dist-info/WHEEL
dsis_client-1.1.0.dist-info/entry_points.txt
dsis_client-1.1.0.dist-info/METADATA
dsis_client-1.1.0.dist-info/RECORD
