Metadata-Version: 2.4
Name: dsis-client
Version: 1.1.0
Summary: A Python client for communicating with DSIS
License-Expression: MIT
License-File: LICENSE
Requires-Dist: msal
Requires-Dist: requests>=2.28.0
Requires-Dist: dsis-schemas[protobuf]>=0.0.5
Requires-Dist: pytest>=7.0.0 ; extra == 'dev'
Requires-Dist: pytest-cov>=4.0.0 ; extra == 'dev'
Requires-Dist: pytest-mock>=3.10.0 ; extra == 'dev'
Requires-Dist: ruff>=0.8.0 ; extra == 'dev'
Requires-Dist: mypy>=1.0.0 ; extra == 'dev'
Requires-Dist: types-requests>=2.28.0 ; extra == 'dev'
Requires-Python: >=3.11
Provides-Extra: dev
